pyoplm/__init__.py
pyoplm/__main__.py
pyoplm/bchunk.py
pyoplm/binmerge.py
pyoplm/bintools.py
pyoplm/common.py
pyoplm/cue2pops_basic_conversion.py
pyoplm/game.py
pyoplm/storage.py
pyoplm/ul.py
pyoplm/opl/__init__.py
pyoplm/opl/args.py
pyoplm/opl/games_manager.py
pyoplm/opl/pyoplm_manager.py
pyoplm-0.71.dist-info/METADATA
pyoplm-0.71.dist-info/WHEEL
pyoplm-0.71.dist-info/entry_points.txt
pyoplm-0.71.dist-info/licenses/LICENSE
pyoplm-0.71.dist-info/RECORD
