Metadata-Version: 2.4
Name: pyoplm
Version: 0.71
Summary: Tool To Manage Open-PS2-Loader USB-Drives & Games
Project-URL: Homepage, https://github.com/edisnord/pyoplm
Author-email: Nold <nold@gnu.one>, edisnord <edisnord@gmail.com>
License-Expression: GPL-3.0-or-later
License-File: LICENSE
Classifier: Operating System :: OS Independent
Classifier: Programming Language :: Python :: 3
Requires-Python: >=3.10
Requires-Dist: beautifulsoup4==4.12.2
Requires-Dist: lxml
Requires-Dist: pillow>=11.0
